kubos/__init__.py
kubos/init.py
kubos/link.py
kubos/main.py
kubos/sdk_config.py
kubos/target.py
kubos/update.py
kubos/use.py
kubos/version.py
kubos/versions.py
kubos/options/__init__.py
kubos/options/command.py
kubos/override/__init__.py
kubos/override/yotta_lib.py
kubos/override/reimplemented_modules/__init__.py
kubos/override/reimplemented_modules/access.py
kubos/override/reimplemented_modules/cmakegen.py
kubos/override/reimplemented_modules/component.py
kubos/override/reimplemented_modules/detect.py
kubos/test/__init__.py
kubos/test/test_build.py
kubos/test/test_clean.py
kubos/test/test_config.py
kubos/test/test_init.py
kubos/test/test_licenses.py
kubos/test/test_link.py
kubos/test/test_list.py
kubos/test/test_outdated.py
kubos/test/test_remove.py
kubos/test/test_sdk_utils.py
kubos/test/test_start.py
kubos/test/test_target.py
kubos/test/test_test.py
kubos/test/test_update.py
kubos/test/utils.py
kubos/utils/__init__.py
kubos/utils/constants.py
kubos/utils/git_common.py
kubos/utils/git_utils.py
kubos/utils/sdk.py
kubos/utils/sdk_utils.py
kubos/utils/status_spinner.py
kubos_cli-0.2.3.dist-info/DESCRIPTION.rst
kubos_cli-0.2.3.dist-info/METADATA
kubos_cli-0.2.3.dist-info/RECORD
kubos_cli-0.2.3.dist-info/WHEEL
kubos_cli-0.2.3.dist-info/entry_points.txt
kubos_cli-0.2.3.dist-info/metadata.json
kubos_cli-0.2.3.dist-info/top_level.txt
