Metadata-Version: 2.0
Name: kubos-cli
Version: 0.2.3
Summary: Kubos CLI
Home-page: http://github.com/kubostech/kubos-cli
Author: Kubos
Author-email: kyle@kubos.co
License: UNKNOWN
Platform: UNKNOWN
Classifier: Programming Language :: Python :: 2.7
Requires-Dist: appdirs
Requires-Dist: argcomplete
Requires-Dist: cryptography
Requires-Dist: gitpython
Requires-Dist: jwt (==0.3.2)
Requires-Dist: ndg-httpsclient
Requires-Dist: packaging
Requires-Dist: pager
Requires-Dist: requests
Requires-Dist: setuptools
Requires-Dist: yotta
